universal_publisher/__init__.py
universal_publisher/main.py
universal_pub-1.1.2.dist-info/METADATA
universal_pub-1.1.2.dist-info/WHEEL
universal_pub-1.1.2.dist-info/top_level.txt
universal_pub-1.1.2.dist-info/RECORD
