Metadata-Version: 2.4
Name: universal-pub
Version: 1.1.2
Summary: A universal ROS2 publisher for text, numbers, booleans, images, videos, and multi-float arrays.
Author: Akshay
Requires-Python: >=3.6
Requires-Dist: cv_bridge
Requires-Dist: opencv-python
Dynamic: author
Dynamic: requires-dist
Dynamic: requires-python
Dynamic: summary
